akms_hash/__init__.py
akms_hash/main.py
akms_hash-0.4.0.dist-info/METADATA
akms_hash-0.4.0.dist-info/WHEEL
akms_hash-0.4.0.dist-info/top_level.txt
akms_hash-0.4.0.dist-info/RECORD
