Metadata-Version: 2.1
Name: akms-hash
Version: 0.4.0
Summary: An API Key hashing library
Home-page: https://github.com/apinanyogaratnam/akms-hash
Author: apinanyogaratnam
Author-email: apinanapinan@icloud.com
Classifier: Programming Language :: Python :: 3
Classifier: License :: OSI Approved :: MIT License
Classifier: Operating System :: OS Independent
Requires-Python: >=3.8
